[
    {
        "team": "Attack",
        "playerNum": "1",
        "posX": 71,
        "posY": 35
    },
    {
        "team": "Attack",
        "playerNum": "2",
        "posX": 40,
        "posY": 27
    },
    {
        "team": "Attack",
        "playerNum": "3",
        "posX": 98,
        "posY": 30
    },
    {
        "team": "Attack",
        "playerNum": "4",
        "posX": 1,
        "posY": 39
    },
    {
        "team": "Attack",
        "playerNum": "5",
        "posX": 2,
        "posY": 35
    },
    {
        "team": "Defense",
        "playerNum": "1",
        "posX": 11,
        "posY": 35
    },
    {
        "team": "Defense",
        "playerNum": "2",
        "posX": 100,
        "posY": 27
    },
    {
        "team": "Defense",
        "playerNum": "3",
        "posX": 65,
        "posY": 30
    },
    {
        "team": "Defense",
        "playerNum": "4",
        "posX": 71,
        "posY": 35
    },
    {
        "team": "Defense",
        "playerNum": "5",
        "posX": 87,
        "posY": 35
    }
]